tec_embrace/__init__.py
tec_embrace/estimate.py
tec_embrace/helper.py
tec_embrace/runtests.py
tec_embrace/settings.py
tec_embrace/tec.py
tec_embrace/app/__init__.py
tec_embrace/app/downloads.py
tec_embrace/app/parser.py
tec_embrace/app/utils/__init__.py
tec_embrace/app/utils/helpers.py
tec_embrace/cycleslip/__init__.py
tec_embrace/cycleslip/cycleslip.py
tec_embrace/tests/__init__.py
tec_embrace/tests/test_downloads.py
tec_embrace/tests/test_estimate.py
tec_embrace/tests/test_helper.py
tec_embrace/tests/test_inputs.py
tec_embrace/tests/test_parser.py
tec_embrace/tests/test_tec.py
tec_embrace-0.2.dist-info/LICENSE
tec_embrace-0.2.dist-info/METADATA
tec_embrace-0.2.dist-info/WHEEL
tec_embrace-0.2.dist-info/top_level.txt
tec_embrace-0.2.dist-info/RECORD
