Metadata-Version: 2.1
Name: tec-embrace
Version: 0.2
Summary: TEC and receiver bias estimation model
Home-page: https://github.com/embrace-inpe/tec
Author: Estudo e Monitoramento Brasileiro do Clima Espacial (EMBRACE/INPE)
Author-email: desenvolvimento.embrace@gmail.com
License: MIT
Platform: UNKNOWN
Classifier: Development Status :: 3 - Alpha
Classifier: Intended Audience :: Developers
Classifier: Topic :: Software Development :: Build Tools
Classifier: License :: OSI Approved :: MIT License
Classifier: Programming Language :: Python :: 3.7
